sqlitepool/__init__.py
sqlitepool/executors.py
sqlitepool-0.0.0.dist-info/licenses/LICENSE
sqlitepool-0.0.0.dist-info/METADATA
sqlitepool-0.0.0.dist-info/WHEEL
sqlitepool-0.0.0.dist-info/top_level.txt
sqlitepool-0.0.0.dist-info/RECORD
