Metadata-Version: 2.4
Name: sqlitepool
Version: 0.0.0
Summary: A thread-pooled sqlite3 for asyncio.
Author-email: Anggit Arfanto <contact@anggit.com>
License-Expression: MIT
Project-URL: Homepage, https://github.com/nggit/sqlitepool
Project-URL: Source, https://github.com/nggit/sqlitepool
Project-URL: Funding, https://github.com/sponsors/nggit
Classifier: Development Status :: 4 - Beta
Classifier: Intended Audience :: Developers
Classifier: Operating System :: OS Independent
Classifier: Topic :: Software Development :: Libraries
Requires-Python: >=3.7
License-File: LICENSE
Dynamic: license-file
